pymontecarlo_gui/__init__.py
pymontecarlo_gui/__main__.py
pymontecarlo_gui/_version.py
pymontecarlo_gui/conftest.py
pymontecarlo_gui/main.py
pymontecarlo_gui/mock.py
pymontecarlo_gui/newsimulation.py
pymontecarlo_gui/project.py
pymontecarlo_gui/settings.py
pymontecarlo_gui/figures/__init__.py
pymontecarlo_gui/figures/sample.py
pymontecarlo_gui/figures/test_sample.py
pymontecarlo_gui/icons/figure.svg
pymontecarlo_gui/icons/logo_32x32.png
pymontecarlo_gui/icons/material-add-advanced.svg
pymontecarlo_gui/icons/material-add-formula.svg
pymontecarlo_gui/icons/newsimulation.svg
pymontecarlo_gui/icons/splash.svg
pymontecarlo_gui/icons/table.svg
pymontecarlo_gui/options/__init__.py
pymontecarlo_gui/options/base.py
pymontecarlo_gui/options/composition.py
pymontecarlo_gui/options/material.py
pymontecarlo_gui/options/options.py
pymontecarlo_gui/options/test_material.py
pymontecarlo_gui/options/analysis/__init__.py
pymontecarlo_gui/options/analysis/base.py
pymontecarlo_gui/options/analysis/kratio.py
pymontecarlo_gui/options/analysis/photon.py
pymontecarlo_gui/options/analysis/photonintensity.py
pymontecarlo_gui/options/beam/__init__.py
pymontecarlo_gui/options/beam/base.py
pymontecarlo_gui/options/beam/cylindrical.py
pymontecarlo_gui/options/beam/gaussian.py
pymontecarlo_gui/options/beam/pencil.py
pymontecarlo_gui/options/detector/__init__.py
pymontecarlo_gui/options/detector/base.py
pymontecarlo_gui/options/detector/photon.py
pymontecarlo_gui/options/detector/test_photon.py
pymontecarlo_gui/options/model/__init__.py
pymontecarlo_gui/options/model/base.py
pymontecarlo_gui/options/model/bremsstrahlung_emission.py
pymontecarlo_gui/options/model/direction_cosine.py
pymontecarlo_gui/options/model/elastic_cross_section.py
pymontecarlo_gui/options/model/energy_loss.py
pymontecarlo_gui/options/model/fluorescence.py
pymontecarlo_gui/options/model/inelastic_cross_section.py
pymontecarlo_gui/options/model/ionization_cross_section.py
pymontecarlo_gui/options/model/ionization_potential.py
pyMonteCarlo_GUI-1.1.0.dist-info/LICENSE
pyMonteCarlo_GUI-1.1.0.dist-info/METADATA
pyMonteCarlo_GUI-1.1.0.dist-info/WHEEL
pyMonteCarlo_GUI-1.1.0.dist-info/entry_points.txt
pyMonteCarlo_GUI-1.1.0.dist-info/top_level.txt
pyMonteCarlo_GUI-1.1.0.dist-info/RECORD
